catwalk/__init__.py
catwalk/db.py
catwalk/evaluation.py
catwalk/feature_importances.py
catwalk/metrics.py
catwalk/model_group_stored_procedure.sql
catwalk/model_trainers.py
catwalk/predictors.py
catwalk/storage.py
catwalk/utils.py
catwalk/estimators/__init__.py
catwalk/estimators/classifiers.py
catwalk/estimators/transformers.py
catwalk/individual_importance/__init__.py
catwalk/individual_importance/uniform.py
model_catwalk-1.0.0.dist-info/DESCRIPTION.rst
model_catwalk-1.0.0.dist-info/METADATA
model_catwalk-1.0.0.dist-info/RECORD
model_catwalk-1.0.0.dist-info/WHEEL
model_catwalk-1.0.0.dist-info/metadata.json
model_catwalk-1.0.0.dist-info/top_level.txt
