Metadata-Version: 2.0
Name: model-catwalk
Version: 1.0.0
Summary: Training, testing, and evaluating machine learning classifier models
Home-page: https://github.com/dssg/catwalk
Author: Center for Data Science and Public Policy
Author-email: datascifellows@gmail.com
License: BY DOWNLOADING catwalk PROGRAM YOU AGREE TO THE FOLLOWING TERMS OF USE:
Requires-Dist: PyYAML
Requires-Dist: SQLAlchemy
Requires-Dist: boto
Requires-Dist: boto3
Requires-Dist: inflection
Requires-Dist: metta-data (>=1.0)
Requires-Dist: numpy (>=1.12)
Requires-Dist: pandas
Requires-Dist: psycopg2
Requires-Dist: python-dateutil
Requires-Dist: results-schema (>=2.0)
Requires-Dist: retrying
Requires-Dist: scikit-learn (==0.18.2)
Requires-Dist: scipy
Requires-Dist: smart-open
Requires-Dist: sqlalchemy-postgres-copy
Requires-Dist: tables (==3.3.0)
